figpager/__init__.py
figpager/figpager.py
figpager/page_layout/default.ini
figpager/page_layout/paper_sizes.ini
figpager-0.32.dist-info/LICENSE.md
figpager-0.32.dist-info/METADATA
figpager-0.32.dist-info/WHEEL
figpager-0.32.dist-info/top_level.txt
figpager-0.32.dist-info/RECORD
