Metadata-Version: 2.1
Name: figpager
Version: 0.32
Summary: A figure page creator class
Home-page: https://github.com/ebenp/figpager
Author: Eben Pendleton
Author-email: 4080051+ebenp@users.noreply.github.com
License: MIT
Project-URL: Code, https://github.com/ebenp/figpager
Project-URL: Issue tracker, https://github.com/ebenp/figpager/issues
Keywords: figure page matplotlib
Platform: UNKNOWN
Classifier: Framework :: Matplotlib
Classifier: License :: OSI Approved :: MIT License
Classifier: Operating System :: OS Independent
Classifier: Programming Language :: Python :: 2.7
Classifier: Programming Language :: Python :: 3.6
Classifier: Programming Language :: Python :: 3.7
Requires-Dist: matplotlib
